[
    {
        "stepId": "STEP1",
        "stepName": "Url: webtours",
        "infFile": "t2.inf",
        "time": 1630527193418
    },
    {
        "stepId": "STEP2",
        "stepName": "Submit Form: login.pl",
        "infFile": "t3.inf",
        "time": 1630527193922
    },
    {
        "stepId": "STEP3",
        "stepName": "Image: Itinerary Button",
        "infFile": "t4.inf",
        "time": 1630527194763
    },
    {
        "stepId": "STEP4",
        "stepName": "Submit Form: itinerary.pl",
        "infFile": "t5.inf",
        "time": 1630527194987
    },
    {
        "stepId": "STEP5",
        "stepName": "Image: SignOff Button",
        "infFile": "t6.inf",
        "time": 1630527195305
    }
]